{
  "updatedAt": "2026-06-12T04:06:34Z",
  "articles": [
    {
      "id": "acd7be4c56d50b1a",
      "title": "How to Earn Bilt Points on Mortgage and HOA Payments \u2014 Without Paying Transaction Fees",
      "summary": "Bilt Rewards offers the opportunity to earn Bilt Points on your mortgage and HOA fees.",
      "url": "https://awardwallet.com/credit-cards/bilt-rewards/earn-bilt-points-mortgage-hoa/?pubDate=2026-06-11",
      "thumbnailUrl": null,
      "category": "Tips",
      "publishedAt": "2026-06-11T23:49:46Z",
      "source": "AwardWallet"
    },
    {
      "id": "d07db5fa3b67c541",
      "title": "American Airlines shopping portal promo: Earn up to 500 bonus miles",
      "summary": "The American Airlines shopping portal is offering up to 500 bonus miles when shopping at both in-store and online retailers.",
      "url": "https://frequentmiler.com/american-airlines-shopping-portal-promo-earn-up-to-500-bonus-miles/",
      "thumbnailUrl": "https://frequentmiler.com/wp-content/uploads/2026/06/AA-Shopping-Portal-Bonus-June.png",
      "category": "Deals",
      "publishedAt": "2026-06-11T22:45:37Z",
      "source": "Frequent Miler"
    },
    {
      "id": "a031bc4e914ae99e",
      "title": "Marriott Bonvoy Boundless\u00ae Credit Card Review: Perks Worth Much More Than Its Annual Fee",
      "summary": "The Marriott Bonvoy Boundless\u00ae Credit Card pays huge dividends to hold over the long term.",
      "url": "https://awardwallet.com/credit-cards/marriott-bonvoy/marriott-bonvoy-boundless/?pubDate=2026-06-11",
      "thumbnailUrl": null,
      "category": "Tips",
      "publishedAt": "2026-06-11T22:10:02Z",
      "source": "AwardWallet"
    },
    {
      "id": "971147f3b8f2f636",
      "title": "Chase Offers/BofA: Save 10% at IHG Brands (Max $57 Cashback)",
      "summary": "Get 10% back on your IHG purchases of $100 or more.",
      "url": "https://www.doctorofcredit.com/bank-amerideals-chase-offers-save-10-at-ihg-brands-max-38-cashback-holiday-inn-inn-express-staybridge-suites-candlewood-suites/",
      "thumbnailUrl": null,
      "category": "Deals",
      "publishedAt": "2026-06-11T21:55:30Z",
      "source": "Doctor of Credit"
    },
    {
      "id": "3cbebb434dcbf46b",
      "title": "Shopping Portal Bonus from Alaska, American Airlines, United (Up To 1,750 Miles)",
      "summary": "American Airlines portal: Earn 500 AAdvantage bonus miles; Alaska portal: Earn 500 Atmos bonus; United portal: Earn 750 bonus miles",
      "url": "https://www.doctorofcredit.com/shopping-portal-bonus-from-alaska-american-airlines-united-up-to-1750-miles/",
      "thumbnailUrl": null,
      "category": "Deals",
      "publishedAt": "2026-06-11T21:46:26Z",
      "source": "Doctor of Credit"
    },
    {
      "id": "86fabf25c3012f5b",
      "title": "Chase Amazon Prime Visa $200 Signup Bonus With No Spend Required",
      "summary": "June 11 through July 9: Signup for Amazon Prime Rewards Visa, get $200 Amazon gift card bonus instantly.",
      "url": "https://www.doctorofcredit.com/chase-amazon-prime-visa-200-signup-bonus-with-no-spend-required-june-11-july-9/",
      "thumbnailUrl": null,
      "category": "Deals",
      "publishedAt": "2026-06-11T20:21:59Z",
      "source": "Doctor of Credit"
    },
    {
      "id": "e9f026893c56be54",
      "title": "Travel-Related Chase Offers: Up to $200 Back on Trafalgar, IHG, Airalo, Cruise America, Turo, And More",
      "summary": "Chase is currently offering a slew of travel-related Chase Offers \u2014 offering potentially hundreds of dollars back on lodging, flights, and\u2026",
      "url": "https://awardwallet.com/news/chase-ultimate-rewards/chase-offers/?pubDate=2026-06-11",
      "thumbnailUrl": null,
      "category": "Deals",
      "publishedAt": "2026-06-11T20:10:02Z",
      "source": "AwardWallet"
    },
    {
      "id": "5fe987ee9dfc2739",
      "title": "$200 Amazon Gift Card upon approval for Prime Visa",
      "summary": "A new limited-time offer has launched exclusively for Amazon Prime members: Get an instant $200 Amazon gift card upon approval for the Amaz\u2026",
      "url": "https://frequentmiler.com/200-amazon-gift-card-upon-approval-for-prime-visa/",
      "thumbnailUrl": "https://frequentmiler.com/wp-content/uploads/2023/05/Amazon-Visa-Dual-Card-Art.jpg",
      "category": "Deals",
      "publishedAt": "2026-06-11T19:45:47Z",
      "source": "Frequent Miler"
    },
    {
      "id": "370a36fb664e5785",
      "title": "AAdvantage Business Promotions: Save 10% on Select Business Class Fares to Asia, Earn 10,000 Miles by Enrolling",
      "summary": "If you haven\u2019t enrolled in the American Airlines AAdvantage\u00ae Business program yet, now\u2019s a great time to do so.",
      "url": "https://awardwallet.com/news/american-aadvantage/aadvantage-business-promotion/?pubDate=2026-06-11",
      "thumbnailUrl": null,
      "category": "Deals",
      "publishedAt": "2026-06-11T19:10:02Z",
      "source": "AwardWallet"
    },
    {
      "id": "87b68149537e3c11",
      "title": "Delta SkyMiles Reserve Business card review: Premium perks for Delta loyalists",
      "summary": "The Delta Reserve Business Amex offers Sky Club access, a companion certificate and Medallion perks.",
      "url": "https://thepointsguy.com/credit-cards/reviews/delta-reserve-amex-review/",
      "thumbnailUrl": "https://runway-media-production.global.ssl.fastly.net/us/originals/2024/08/Planes-PIT-28.jpg",
      "category": "Tips",
      "publishedAt": "2026-06-11T19:00:30Z",
      "source": "The Points Guy"
    },
    {
      "id": "68dfbeb849387e93",
      "title": "American Airlines Promotions: Earn 25k Bonus Miles by Switching Your Cell Service to AT&T",
      "summary": "Every now and then, American Airlines launches a promotion with bonus miles.",
      "url": "https://awardwallet.com/news/american-aadvantage/earn-bonus-miles/?pubDate=2026-06-11",
      "thumbnailUrl": null,
      "category": "Deals",
      "publishedAt": "2026-06-11T18:10:02Z",
      "source": "AwardWallet"
    },
    {
      "id": "1a186ecb5c1edd53",
      "title": "Airlines Are Offering Huge Credit Card Bonuses This Summer \u2014 But Do They Make Sense?",
      "summary": "If it feels like every airline is dangling a big credit card bonus right now, you\u2019re not imagining it.",
      "url": "https://onemileatatime.com/insights/inflation-brings-big-travel-credit-card-offers/",
      "thumbnailUrl": "https://cdn.onemileatatime.com/wp-content/uploads/2025/07/New-American-Business-Class-787-6.jpeg?width=1200&quality=75&height=900&aspect_ratio=4%3A3",
      "category": "Deals",
      "publishedAt": "2026-06-11T18:05:06Z",
      "source": "One Mile at a Time"
    },
    {
      "id": "0ab415ba59735fad",
      "title": "Delta promo: Earn 20% bonus MQDs when booking Extra seats (targeted?)",
      "summary": "Delta is targeting some SkyMiles members with an opportunity to earn 20% bonus Medallion Qualification Dollars (MQDs) when booking Extra se\u2026",
      "url": "https://frequentmiler.com/delta-promo-earn-20-bonus-mqds-when-booking-extra-seats-targeted/",
      "thumbnailUrl": "https://frequentmiler.com/wp-content/uploads/2026/06/Delta-20-bonus-Medallion-Qualification-Dollars-MQDs.jpg",
      "category": "Deals",
      "publishedAt": "2026-06-11T17:45:36Z",
      "source": "Frequent Miler"
    },
    {
      "id": "c290c1c4ea9e4bde",
      "title": "Schwab Investor Card from American Express $300 Sign Up Bonus",
      "summary": "Schwab Investor Card from American Express is offering a sign up bonus of $300 after $1,000 in spend within the first three months of Card\u2026",
      "url": "https://www.doctorofcredit.com/schwab-investor-card-from-american-express-300-sign-up-bonus/",
      "thumbnailUrl": null,
      "category": "Deals",
      "publishedAt": "2026-06-11T17:00:41Z",
      "source": "Doctor of Credit"
    },
    {
      "id": "a8f862afec48d619",
      "title": "Sign up for Rakuten and Earn $50 or 5,000 Amex or Bilt Points After Spending $50 \u2014 and Score Deals Throughout Travel Week",
      "summary": "Rakuten is one of the oldest \u2014 and remains one of the best \u2014 shopping portals on the internet for earning bonus rewards.",
      "url": "https://awardwallet.com/shopping/rakuten-rewards/?pubDate=2026-06-11",
      "thumbnailUrl": null,
      "category": "Deals",
      "publishedAt": "2026-06-11T16:40:03Z",
      "source": "AwardWallet"
    },
    {
      "id": "51a42d4891d72139",
      "title": "[Targeted] PayPal Rewards: Use Pay Later & Get 5% Back (Up To $10)",
      "summary": "PayPal Rewards is offering 15% back in rewards when you use Pay later for the first time.",
      "url": "https://www.doctorofcredit.com/targeted-paypal-rewards-use-pay-later-get-5-back-up-to-10/",
      "thumbnailUrl": null,
      "category": "Deals",
      "publishedAt": "2026-06-11T16:00:48Z",
      "source": "Doctor of Credit"
    },
    {
      "id": "f4df8122b1b170d2",
      "title": "How to transfer Avios between British Airways, Qatar, Iberia, Aer Lingus, Finnair and Loganair",
      "summary": "British Airways, Qatar, Aer Lingus, Iberia, Finnair, regional Scottish airline Loganair, and Vueling (a low-cost carrier) all share a commo\u2026",
      "url": "https://frequentmiler.com/how-to-transfer-avios-between-programs/",
      "thumbnailUrl": "https://frequentmiler.com/wp-content/uploads/2018/09/Avios.jpg",
      "category": "Tips",
      "publishedAt": "2026-06-11T15:45:30Z",
      "source": "Frequent Miler"
    },
    {
      "id": "f351e7606abb0c28",
      "title": "Flying Blue Gold Status Match Ends Saturday, Unlocking Free Delta Bags, Boarding, And Exit Rows",
      "summary": "Flying Blue Gold status match ends Saturday for U.S.",
      "url": "https://viewfromthewing.com/flying-blue-gold-status-match-ends-saturday-unlocking-free-delta-bags-boarding-and-exit-rows/",
      "thumbnailUrl": "https://viewfromthewing.com/wp-content/uploads/2025/03/20250321_0943240.jpg",
      "category": "News",
      "publishedAt": "2026-06-11T14:25:43Z",
      "source": "View from the Wing"
    },
    {
      "id": "15158b5416cf95fc",
      "title": "Credit One Wander American Express \u2013 5% Back On Gas, Restaurants & Travel",
      "summary": "On our recent post about the \u2018Credit One Platinum X5 Card\u2018 reader Jags shared that there is a more interesting Credit One card called \u2018Cred\u2026",
      "url": "https://www.doctorofcredit.com/credit-one-wander-american-express-5-back-on-gas-restaurants-travel/",
      "thumbnailUrl": null,
      "category": "Deals",
      "publishedAt": "2026-06-11T14:00:36Z",
      "source": "Doctor of Credit"
    },
    {
      "id": "afc3fc92c920bf72",
      "title": "Air France-KLM Flying Blue Paid Status Match Promotion: Eligibility, Cost, Value",
      "summary": "For quite some time, Air France-KLM Flying Blue has been offering paid status match promotions, on an on-again, off-again basis.",
      "url": "https://onemileatatime.com/deals/air-france-klm-flying-blue-status-match/",
      "thumbnailUrl": "https://cdn.onemileatatime.com/wp-content/uploads/2024/04/KLM-Crown-Lounge-Amsterdam-12.jpeg?width=1200&quality=75&height=900&aspect_ratio=4%3A3",
      "category": "Deals",
      "publishedAt": "2026-06-11T13:59:22Z",
      "source": "One Mile at a Time"
    },
    {
      "id": "f27a38f08faf97c2",
      "title": "Capital One Venture Business Card: New 100K welcome offer",
      "summary": "Capital One rebranded and revamped the Spark Miles for Business card a couple of months ago, and it\u2019s now known as the Venture Business car\u2026",
      "url": "https://frequentmiler.com/capital-one-venture-business-card-100k-welcome-offer/",
      "thumbnailUrl": "https://frequentmiler.com/wp-content/uploads/2026/06/Capital-Venture-Business-Card-Art.jpg",
      "category": "Card Updates",
      "publishedAt": "2026-06-11T13:45:53Z",
      "source": "Frequent Miler"
    },
    {
      "id": "c103866bf05bade7",
      "title": "[Targeted] Robinhood: Up To $1,250 New User Bonus (30 Day Hold Period)",
      "summary": "Robinhood is offering a new user sign up bonus of up to $1,250.",
      "url": "https://www.doctorofcredit.com/targeted-robinhood-up-to-1250-new-user-bonus-30-day-hold-period/",
      "thumbnailUrl": null,
      "category": "Deals",
      "publishedAt": "2026-06-11T13:00:34Z",
      "source": "Doctor of Credit"
    },
    {
      "id": "6ef9f746da2fb452",
      "title": "Easy Points: Earn 1,000 Qatar Airways Avios on Your Next Hilton Stay",
      "summary": "Hilton and Qatar Airways have relaunched their annual promotion, giving travelers a chance to earn bonus Avios on Hilton stays.",
      "url": "https://awardwallet.com/news/hilton-honors/bonus-airline-miles-promotion/?pubDate=2026-06-11",
      "thumbnailUrl": null,
      "category": "Deals",
      "publishedAt": "2026-06-11T12:17:46Z",
      "source": "AwardWallet"
    },
    {
      "id": "e10403855a71a27e",
      "title": "Save At Auberge Collection With Amex Offers (Targeted)",
      "summary": "The Amex Offers program frequently has promotions for hotel stays, which can save you money or earn you bonus points for stays youd make an\u2026",
      "url": "https://onemileatatime.com/deals/auberge-collection-amex-offers/",
      "thumbnailUrl": "https://cdn.onemileatatime.com/wp-content/uploads/2023/04/The-Woodward-Hotel-Geneva-48.jpeg?width=1200&quality=75&height=900&aspect_ratio=4%3A3",
      "category": "Deals",
      "publishedAt": "2026-06-11T08:54:25Z",
      "source": "One Mile at a Time"
    },
    {
      "id": "b63cd65c0f555a54",
      "title": "My take on the refreshed Sapphire Preferred Card",
      "summary": "Chase has announced big changes to the Sapphire Preferred\u00ae Card, starting June 15th.",
      "url": "https://frequentmiler.com/my-take-on-the-refreshed-sapphire-preferred-card/",
      "thumbnailUrl": "https://frequentmiler.com/wp-content/uploads/2026/06/Sapphire-Reserve-Refresh-Chalkboard.jpg",
      "category": "Card Updates",
      "publishedAt": "2026-06-11T01:45:53Z",
      "source": "Frequent Miler"
    },
    {
      "id": "4da416fa2b2b523b",
      "title": "Amex Refer a Friend Program: Earn Bonus Points or Cash Back on Card Referrals",
      "summary": "American Express allows Card Members to refer their cards to others in exchange for bonus points, miles, or cash back.",
      "url": "https://awardwallet.com/credit-cards/amex-refer-a-friend/?pubDate=2026-06-11",
      "thumbnailUrl": null,
      "category": "Deals",
      "publishedAt": "2026-06-11T00:00:05Z",
      "source": "AwardWallet"
    },
    {
      "id": "0d3f39fe3a4d32a1",
      "title": "Qatar business class open from US \u2013 Doha starting in August 2026",
      "summary": "Qatar Airways will be restarting service from Philadelphia to Doha this August, which has caused a decent bit of business class availabilit\u2026",
      "url": "https://frequentmiler.com/qatar-business-class-open-from-us-doha-starting-in-august-2026/",
      "thumbnailUrl": "https://frequentmiler.com/wp-content/uploads/2025/03/Qatar-Airways-featured-image-with-people.jpg",
      "category": "Deals",
      "publishedAt": "2026-06-10T23:45:52Z",
      "source": "Frequent Miler"
    },
    {
      "id": "197426dea74b171d",
      "title": "Buy Southwest Rapid Rewards Points With up to a 45% Discount Through July 22",
      "summary": "Southwest just launched a promotion to buy Rapid Rewards points with an up-to-45% discount.",
      "url": "https://awardwallet.com/airlines/southwest-rapid-rewards/buy-southwest-points/?pubDate=2026-06-10",
      "thumbnailUrl": null,
      "category": "Deals",
      "publishedAt": "2026-06-10T22:10:02Z",
      "source": "AwardWallet"
    },
    {
      "id": "481c5e6b77cacef8",
      "title": "How I saved over $8,000 on a family trip to Paris with the Chase Sapphire Reserve",
      "summary": "See how Chase Sapphire Reserve's 150K-point offer could help cover flights, hotels and more on a family trip to Paris during peak season.",
      "url": "https://thepointsguy.com/credit-cards/family-trip-to-paris-with-chase-sapphire-reserve/",
      "thumbnailUrl": "https://runway-media-production.global.ssl.fastly.net/us/originals/2026/06/IMG_2171.jpg",
      "category": "Deals",
      "publishedAt": "2026-06-10T22:00:46Z",
      "source": "The Points Guy"
    },
    {
      "id": "0f7b94e4d6d61674",
      "title": "Buy Hilton Points For 0.5 Cents Each",
      "summary": "Hilton has returned with a new sale offering members an up to 100% bonus when purchasing Hilton Honors points.",
      "url": "https://frequentmiler.com/buy-hilton-points/",
      "thumbnailUrl": "https://frequentmiler.com/wp-content/uploads/2019/09/Conrad-Bora-Bora-beach-boat.jpg",
      "category": "Deals",
      "publishedAt": "2026-06-10T21:45:33Z",
      "source": "Frequent Miler"
    },
    {
      "id": "2783221558b750c4",
      "title": "Marriott Homes & Villas Promotions: New Offers for Double Points, Triple Points, and 10k Bonus Points on Stays",
      "summary": "If you're considering a trip, now is a great time to book a stay through Marriott Homes & Villas.",
      "url": "https://awardwallet.com/news/marriott-bonvoy/marriott-homes-and-villas-promotions/?pubDate=2026-06-10",
      "thumbnailUrl": null,
      "category": "Deals",
      "publishedAt": "2026-06-10T21:10:02Z",
      "source": "AwardWallet"
    },
    {
      "id": "8114c835ff6636df",
      "title": "Subscribe to Accor+ Explorer for 2,000 Bonus Points \u2014 and Score Perks at Select Accor Hotels",
      "summary": "For a limited time, Accor Live Limitless (ALL) members can sign up for a new Accor+ Explorer subscription and receive 2,000 bonus points.",
      "url": "https://awardwallet.com/news/accor-live-limitless/accor-plus-promotion/?pubDate=2026-06-10",
      "thumbnailUrl": null,
      "category": "Deals",
      "publishedAt": "2026-06-10T20:10:02Z",
      "source": "AwardWallet"
    },
    {
      "id": "a685a2fcfcde64d8",
      "title": "Points Path works beyond Google Flights: Here's where else you can use it",
      "summary": "Points Path works beyond Google Flights with opt-in features for Chase Travel Points Boost and hotel price comparisons.",
      "url": "https://thepointsguy.com/news/points-path-chase-points-boost-hotel-comparison/",
      "thumbnailUrl": "https://runway-media-production.global.ssl.fastly.net/us/originals/2026/06/GettyImages-2155062003.jpg",
      "category": "Tips",
      "publishedAt": "2026-06-10T20:00:39Z",
      "source": "The Points Guy"
    },
    {
      "id": "931f910f6b8a7319",
      "title": "TopCashback: Get a 2% bonus when cashing out earnings to Venmo (ends 6/12)",
      "summary": "TopCashback is running a flash promotion that\u2019s boosting your shopping portal earnings by 2% when cashing out to your Venmo account.",
      "url": "https://frequentmiler.com/topcashback-venmo-bonus/",
      "thumbnailUrl": "https://frequentmiler.com/wp-content/uploads/2026/06/TopCashback-Venmo-2-bonus.jpg",
      "category": "Deals",
      "publishedAt": "2026-06-10T19:45:05Z",
      "source": "Frequent Miler"
    },
    {
      "id": "a945f4e7e0465ef5",
      "title": "Chase INK Cash & INK Unlimited 100,000 Points Signup Bonus (Starts June 15th)",
      "summary": "Chase INK Business Cash and INK Business Unlimited card signup bonus of 100,000 points after spending $8,000 within four months (starts Jun\u2026",
      "url": "https://www.doctorofcredit.com/chase-ink-cash-ink-unlimited-100000-points-signup-bonus-starts-june-15th/",
      "thumbnailUrl": null,
      "category": "Deals",
      "publishedAt": "2026-06-10T19:17:01Z",
      "source": "Doctor of Credit"
    },
    {
      "id": "207d05feaa31c45c",
      "title": "United-American Merger Talk Still Alive As American Airlines CEO Fights It At Shareholder Meeting",
      "summary": "American Airlines CEO Robert Isom pushed back against a United merger at the shareholder meeting, showing Scott Kirby\u2019s pressure campaign s\u2026",
      "url": "https://viewfromthewing.com/united-american-merger-talk-still-alive-as-american-airlines-ceo-fights-it-at-shareholder-meeting/",
      "thumbnailUrl": "https://viewfromthewing.com/wp-content/uploads/2026/04/united-airlines-american-airlines.jpg",
      "category": "News",
      "publishedAt": "2026-06-10T19:13:07Z",
      "source": "View from the Wing"
    },
    {
      "id": "c53b900bb449f9a0",
      "title": "Hyatt Is Cashing In On Loyalty: Smart Business Decision, Or Will It Backfire?",
      "summary": "World of Hyatt has long been my favorite major hotel loyalty program.",
      "url": "https://onemileatatime.com/insights/hyatt-cashing-in-loyalty/",
      "thumbnailUrl": "https://cdn.onemileatatime.com/wp-content/uploads/2023/10/Park-Hyatt-Kyoto-10.jpeg?width=1200&quality=75&height=879&aspect_ratio=400%3A293",
      "category": "Tips",
      "publishedAt": "2026-06-10T18:59:43Z",
      "source": "One Mile at a Time"
    },
    {
      "id": "7bcd62a1c71d71fe",
      "title": "Chase Sapphire Reserve for Business: 200,000 Points Sign Up Bonus (Starts 6/15)",
      "summary": "(starts 6/15/26) Chase Sapphire Reserve for Business card will offer a signup bonus of 200,000 points after $30,000 in spend within the fir\u2026",
      "url": "https://www.doctorofcredit.com/chase-sapphire-reserve-for-business-200000-points-sign-up-bonus-starts-6-15/",
      "thumbnailUrl": null,
      "category": "Deals",
      "publishedAt": "2026-06-10T18:56:21Z",
      "source": "Doctor of Credit"
    },
    {
      "id": "756fd1ad095cc20d",
      "title": "Marriott/Outside partnership: Earn 1,000 bonus points with subscription, 50 bonus points per activity, & more",
      "summary": "Marriott recently launched a new partnership with outdoor activity company Outside.",
      "url": "https://frequentmiler.com/marriott-outside-partnership-earn-1000-bonus-points-with-subscription-50-bonus-points-per-activity-more/",
      "thumbnailUrl": "https://frequentmiler.com/wp-content/uploads/2026/06/Marriott-Bonvoy-Outside-partnership.jpg",
      "category": "News",
      "publishedAt": "2026-06-10T18:45:46Z",
      "source": "Frequent Miler"
    },
    {
      "id": "e39320f906497871",
      "title": "Hyatt Under Canvas Promotions: Earn 2k Bonus Points per Night, 20X Points on Spending, and AAdvantage Miles",
      "summary": "It's not very often you can mention national parks, glamping, and bonus points in the same sentence.",
      "url": "https://awardwallet.com/news/world-of-hyatt/under-canvas-promotions/?pubDate=2026-06-10",
      "thumbnailUrl": null,
      "category": "Deals",
      "publishedAt": "2026-06-10T18:10:02Z",
      "source": "AwardWallet"
    },
    {
      "id": "6c19466f9f8573eb",
      "title": "Last chance to activate Chase Freedom Q2 categories: 5% back on Amazon, Chase Travel, Feeding America and Whole Foods",
      "summary": "You won't want to miss out on a single point \u2014 or cent of cash back \u2014 on your spending.",
      "url": "https://thepointsguy.com/credit-cards/activate-chase-freedom-5x-earnings/",
      "thumbnailUrl": "https://runway-media-production.global.ssl.fastly.net/us/originals/2021/07/Shopping_Tom-Werner.jpg",
      "category": "Deals",
      "publishedAt": "2026-06-10T18:00:59Z",
      "source": "The Points Guy"
    },
    {
      "id": "2423428c17555471",
      "title": "Homes & Villas by Marriott promo: Earn 10K bonus points on 2+ night, $1,500+ stay in the mountains",
      "summary": "Homes & Villas by Marriott is running another promotion, this time offering 10,000 bonus Marriott Bonvoy points when booking a stay in the\u2026",
      "url": "https://frequentmiler.com/homes-villas-by-marriott-promo-earn-10k-bonus-points-on-2-night-1500-stay-in-the-mountains/",
      "thumbnailUrl": "https://frequentmiler.com/wp-content/uploads/2026/06/Marriott-Homes-Villas-10K-bonus-points-stays-in-mountains.jpg",
      "category": "Deals",
      "publishedAt": "2026-06-10T17:45:39Z",
      "source": "Frequent Miler"
    },
    {
      "id": "cae880ed603f2e22",
      "title": "Accor promo: Earn 2X points on meetings & events",
      "summary": "Accor has a promotion that\u2019s running through the end of the year that awards double points on all ALL your meetings and events.",
      "url": "https://frequentmiler.com/accor-promo-earn-2x-points-on-meetings-events/",
      "thumbnailUrl": "https://frequentmiler.com/wp-content/uploads/2026/06/Accor-promotion-double-points-meetings-events.png",
      "category": "Deals",
      "publishedAt": "2026-06-10T16:45:29Z",
      "source": "Frequent Miler"
    },
    {
      "id": "aa8b47243708b4a5",
      "title": "Buy Hilton Honors Points With up to a 100% Bonus (0.5\u00a2 Each)",
      "summary": "Hilton Honors is offering a 100% bonus on purchased points \u2014 dropping the rate of buying Hilton points to 0.5\u00a2 per point.",
      "url": "https://awardwallet.com/hotels/hilton-honors/buy-hilton-points/?pubDate=2026-06-10",
      "thumbnailUrl": null,
      "category": "Deals",
      "publishedAt": "2026-06-10T16:10:02Z",
      "source": "AwardWallet"
    },
    {
      "id": "4c0ad937f7f5d653",
      "title": "Chase $100-$200 Savings Bonus",
      "summary": "Chase is offering a savings bonus of up to $200.",
      "url": "https://www.doctorofcredit.com/chase-100-200-savings-bonus/",
      "thumbnailUrl": null,
      "category": "Deals",
      "publishedAt": "2026-06-10T16:00:21Z",
      "source": "Doctor of Credit"
    },
    {
      "id": "269c278f9512963d",
      "title": "United CEO Refuses To Say American Airlines Merger Is Dead, And Keeps Talking Up JetBlue",
      "summary": "United CEO Scott Kirby still won\u2019t declare an American Airlines merger dead, keeps praising JetBlue as a partner, and now admits United ord\u2026",
      "url": "https://viewfromthewing.com/united-ceo-refuses-to-say-american-airlines-merger-is-dead-and-keeps-talking-up-jetblue/",
      "thumbnailUrl": "https://viewfromthewing.com/wp-content/uploads/2022/07/20220619_120532-scaled.jpg",
      "category": "News",
      "publishedAt": "2026-06-10T15:58:14Z",
      "source": "View from the Wing"
    },
    {
      "id": "11b230dad2c2c7fb",
      "title": "Kroger: Earn 4x fuel points on 3rd party and fixed-value Visa / Mastercard gift cards",
      "summary": "Kroger is once again running a promotion that awards 4x fuel points on third-party gift cards, whether purchased online or in-store, and fi\u2026",
      "url": "https://frequentmiler.com/kroger-earn-4x-fuel-points-on-3rd-party-gift-cards-fixed-value-visa-mastercard-gift-cards/",
      "thumbnailUrl": "https://frequentmiler.com/wp-content/uploads/2018/04/Kroger-Gift-Card-Rack.jpg",
      "category": "Deals",
      "publishedAt": "2026-06-10T15:45:23Z",
      "source": "Frequent Miler"
    },
    {
      "id": "041a03d941185a34",
      "title": "Capital One's Dulles lounge will close many interior spaces for months",
      "summary": "Starting July 9, the Capital One Lounge at IAD will temporarily transition to a limited-service model.",
      "url": "https://thepointsguy.com/news/capital-ones-dulles-lounge-closing-renovations/",
      "thumbnailUrl": "https://runway-media-production.global.ssl.fastly.net/us/originals/2023/09/20230831_Capital-Lounge-Dulles_SHull_49.jpg",
      "category": "News",
      "publishedAt": "2026-06-10T15:36:03Z",
      "source": "The Points Guy"
    },
    {
      "id": "6309e10da424dd1f",
      "title": "Capital One Savor credit card review: A no-annual-fee card for food and entertainment",
      "summary": "Looking to earn cash back on dining and entertainment spending?",
      "url": "https://thepointsguy.com/credit-cards/reviews/capital-one-savor-review/",
      "thumbnailUrl": "https://runway-media-production.global.ssl.fastly.net/us/originals/2023/11/Country-Music-Awards-concert-at-Allegiant-Stadium-in-Las-Vegas-Nevada_Ethan-MillerGetty-Images.jpg",
      "category": "Tips",
      "publishedAt": "2026-06-10T15:00:14Z",
      "source": "The Points Guy"
    },
    {
      "id": "e8e30536d542ec7f",
      "title": "Choice Privileges Experiences: Bid on Canadian Football League tickets which include $250 merch cards",
      "summary": "Choice Privileges Experiences has a couple of new auctions you can bid on for Canadian Football League games.",
      "url": "https://frequentmiler.com/choice-privileges-experiences-bid-on-canadian-football-league-tickets-which-include-250-merch-cards/",
      "thumbnailUrl": "https://frequentmiler.com/wp-content/uploads/2026/06/Choice-Privileges-CFL-auction.jpg",
      "category": "Deals",
      "publishedAt": "2026-06-10T14:45:47Z",
      "source": "Frequent Miler"
    }
  ]
}
