{
  "updatedAt": "2026-05-27T15:46:58Z",
  "articles": [
    {
      "id": "34e6f305acea72c5",
      "title": "Unlock Surprisingly Cheap Hotel Nights With Wyndham\u2019s 80% Buy Points Bonus",
      "summary": "Wyndham Rewards is offering a promotion to buy points at a solid rate.",
      "url": "https://awardwallet.com/hotels/wyndham-rewards/buy-wyndham-points/?pubDate=2026-05-27",
      "thumbnailUrl": null,
      "category": "Deals",
      "publishedAt": "2026-05-27T15:10:02Z",
      "source": "AwardWallet"
    },
    {
      "id": "634dae49e1751afd",
      "title": "Newegg: Save 10% On Olive Garden Giftcards \u2013 Stack With Chase Paze Promo (SSF68998)",
      "summary": "Newegg.com is selling Olive Garden $50 e-gift cards for $45.",
      "url": "https://www.doctorofcredit.com/newegg-save-10-on-olive-garden-giftcards-stack-with-chase-paze-promo-ssf68998/",
      "thumbnailUrl": null,
      "category": "Deals",
      "publishedAt": "2026-05-27T14:43:47Z",
      "source": "Doctor of Credit"
    },
    {
      "id": "9c6b8ddea069732f",
      "title": "Meijer Mperks: 10,000 Points On $100 Visa Giftcard (Valid Until 6/2)",
      "summary": "Update 5/27/26: Deal is back through June 2nd.",
      "url": "https://www.doctorofcredit.com/meijer-mperks-10-off-150-visa-giftcards-7/",
      "thumbnailUrl": null,
      "category": "Deals",
      "publishedAt": "2026-05-27T14:15:00Z",
      "source": "Doctor of Credit"
    },
    {
      "id": "338afdffb86ce572",
      "title": "Is The Amex Platinum Card Worth It? How I Get The Most Value",
      "summary": "In 2025, the American Express Platinum Card (application) went through a major refresh that pushed the $895 annual fee ( Rates & Fees ) to\u2026",
      "url": "https://onemileatatime.com/insights/american-express-platinum-card-worth-it/",
      "thumbnailUrl": "https://cdn.onemileatatime.com/wp-content/uploads/2025/07/Park-Hyatt-London-River-Thames-20.jpeg?width=1200&quality=75&height=920&aspect_ratio=30%3A23",
      "category": "Tips",
      "publishedAt": "2026-05-27T14:11:32Z",
      "source": "One Mile at a Time"
    },
    {
      "id": "5f982a6884bea374",
      "title": "Bestbuy.com: 20% Off Fandango & Fandango At Home Giftcards",
      "summary": "Bestbuy.com is selling Fandango and Fandango At Home e-gift cards at a 20% discount.",
      "url": "https://www.doctorofcredit.com/bestbuy-com-20-off-fandango-fandango-at-home-giftcards/",
      "thumbnailUrl": null,
      "category": "Deals",
      "publishedAt": "2026-05-27T14:06:19Z",
      "source": "Doctor of Credit"
    },
    {
      "id": "d4e5aa4e342c9168",
      "title": "Get $50 off $300+ Citi Travel hotel booking; stack with other Citi credits",
      "summary": "To celebrate the third birthday of Citi Travel, Citi is giving eligible cardholders $50 off when booking a $300+ hotel stay via Citi Travel.",
      "url": "https://frequentmiler.com/get-50-off-300-citi-travel-hotel-booking-stack-with-other-citi-credits/",
      "thumbnailUrl": "https://frequentmiler.com/wp-content/uploads/2026/05/Citi-Travel-50-off-300.jpg",
      "category": "Deals",
      "publishedAt": "2026-05-27T13:45:09Z",
      "source": "Frequent Miler"
    },
    {
      "id": "30868b8bce09a59b",
      "title": "Your guide to the Chase Ink Business credit cards",
      "summary": "Are you considering a business credit card?",
      "url": "https://thepointsguy.com/credit-cards/chase-ink-card-showdown/",
      "thumbnailUrl": "https://runway-media-production.global.ssl.fastly.net/us/originals/2023/11/Business-partners-looking-at-computer-in-office_FG-Trade.jpg",
      "category": "Tips",
      "publishedAt": "2026-05-27T13:30:50Z",
      "source": "The Points Guy"
    },
    {
      "id": "8732932d45e80658",
      "title": "Bilt Rent Day June 2026: Business Class to Europe From 45k Bilt Points, Free Rent, and More",
      "summary": "This month's Bilt Rent Day on June 1 features up to a 125% transfer bonus to TAP Miles&Go Miles.",
      "url": "https://awardwallet.com/news/bilt-rewards/bilt-rent-day/?pubDate=2026-05-27",
      "thumbnailUrl": null,
      "category": "Deals",
      "publishedAt": "2026-05-27T13:10:22Z",
      "source": "AwardWallet"
    },
    {
      "id": "ba0f48856757e510",
      "title": "Bilt Rent Day Promotion June 2026: Up To 125% TAP Air Portugal Transfer Bonus",
      "summary": "Bilt is the platform known for providing rewards for housing payments.",
      "url": "https://onemileatatime.com/guides/bilt-rent-day-promotion/",
      "thumbnailUrl": "https://cdn.onemileatatime.com/wp-content/uploads/2024/05/TAP-Air-Portugal-Business-Class-A320neo-4-1.jpeg?width=1200&quality=75&height=856&aspect_ratio=150%3A107",
      "category": "Deals",
      "publishedAt": "2026-05-27T13:01:44Z",
      "source": "One Mile at a Time"
    },
    {
      "id": "d5dbe927360ff713",
      "title": "Bilt Rent Day Goes Full Madonna \u2014 Up To 125% TAP Transfer Bonus And Rent Paid For Her Old Building",
      "summary": "Bilt\u2019s June Rent Day is built around Madonna, with custom vinyl, album-release events and even a full month of rent covered at the New York\u2026",
      "url": "https://viewfromthewing.com/bilt-rent-day-goes-full-madonna-up-to-125-tap-transfer-bonus-and-rent-paid-for-her-old-building/",
      "thumbnailUrl": "https://viewfromthewing.com/wp-content/uploads/2025/11/tap-air-portugal.jpeg",
      "category": "Deals",
      "publishedAt": "2026-05-27T13:00:04Z",
      "source": "View from the Wing"
    },
    {
      "id": "9b2098bca90bf07d",
      "title": "[Targeted] Citi: Spend $300 On Hotels, Get $30 Credit",
      "summary": "Check your Citi Offers: Spend $350 at Airlines through 08/15/2022 and earn $30 back.",
      "url": "https://www.doctorofcredit.com/targeted-citi-offers-spend-350-on-airlines-hotels-get-30-credit/",
      "thumbnailUrl": null,
      "category": "Deals",
      "publishedAt": "2026-05-27T12:00:45Z",
      "source": "Doctor of Credit"
    },
    {
      "id": "6812aa6e5bbeff98",
      "title": "Citi Cardholders Have 3 Days To Stack A $50 Hotel Deal With Up To $300 In Annual Credits",
      "summary": "This is a pretty good deal.",
      "url": "https://viewfromthewing.com/citi-cardholders-have-3-days-to-stack-a-50-hotel-deal-with-up-to-300-in-annual-credits/",
      "thumbnailUrl": "https://viewfromthewing.com/wp-content/uploads/2017/10/20171013_185023.jpg",
      "category": "Deals",
      "publishedAt": "2026-05-27T11:04:18Z",
      "source": "View from the Wing"
    },
    {
      "id": "464e6e3960304c60",
      "title": "My week in travel, made better by ultra-premium cards",
      "summary": "Over the past year, I\u2019ve lamented the fact that rising ultra-premium card annual fees have made me melt.",
      "url": "https://frequentmiler.com/my-week-in-travel-made-better-by-ultra-premium-cards/",
      "thumbnailUrl": "https://frequentmiler.com/wp-content/uploads/2026/05/Amex-Sidecar-Lounge-Entrance.jpg",
      "category": "Tips",
      "publishedAt": "2026-05-27T10:45:01Z",
      "source": "Frequent Miler"
    },
    {
      "id": "2c0a4c73da9d7fda",
      "title": "Citi Travel offers limited-time hotel deal: Save $50 on bookings over $300",
      "summary": "Eligible Citi cardmembers can save $50 on prepaid hotel bookings through Citi Travel during a new three-day promotion.",
      "url": "https://thepointsguy.com/news/citi-travel-hotel-deal-save-50/",
      "thumbnailUrl": "https://runway-media-production.global.ssl.fastly.net/us/originals/2025/12/Best-New-Hotels-2026_casabrera3.jpg",
      "category": "Deals",
      "publishedAt": "2026-05-27T10:00:40Z",
      "source": "The Points Guy"
    },
    {
      "id": "af80d2074babd381",
      "title": "Citi Cardholders Can Save $50 on Citi Travel Hotel Bookings for a Limited Time \u2014 Here\u2019s How",
      "summary": "To celebrate its three-year anniversary, Citi Travel is offering a special promotion to eligible Citi cardholders.",
      "url": "https://awardwallet.com/news/citi-thankyou-rewards/citi-travel-savings/?pubDate=2026-05-27",
      "thumbnailUrl": null,
      "category": "Deals",
      "publishedAt": "2026-05-27T10:00:12Z",
      "source": "AwardWallet"
    },
    {
      "id": "1694e262f247eee0",
      "title": "Homes & Villas by Marriott promo: Earn 3X points on 5+ night stays in Caribbean & Latin America",
      "summary": "Homes & Villas by Marriott tends to have some kind of promotion running nearly every day of the year in one form or another.",
      "url": "https://frequentmiler.com/homes-villas-by-marriott-promo-earn-3x-points-on-5-night-stays-in-caribbean-latin-america/",
      "thumbnailUrl": "https://frequentmiler.com/wp-content/uploads/2026/05/Homes-Villas-by-Marriott-promotion-3x-points-5-nights-Caribbean-Latin-America.jpg",
      "category": "Deals",
      "publishedAt": "2026-05-26T23:45:26Z",
      "source": "Frequent Miler"
    },
    {
      "id": "bf740fc0546fa65c",
      "title": "[Targeted] AmEx Offer: Caesars Entertainment, Spend $200+ & Receive $40 Statement Credit",
      "summary": "Update 5/26/26: Deal is back until August 31, 2026.",
      "url": "https://www.doctorofcredit.com/targeted-amex-offer-caesars-entertainment-spend-200-receive-40-statement-credit/",
      "thumbnailUrl": null,
      "category": "Deals",
      "publishedAt": "2026-05-26T23:22:20Z",
      "source": "Doctor of Credit"
    },
    {
      "id": "98402c464a7bcde8",
      "title": "First impressions of the new World of Hyatt order | Coffee Break Ep107 | 5-26-26",
      "summary": "The World of Hyatt new award charts are live now, and we have thoughts!",
      "url": "https://frequentmiler.com/first-impressions-of-the-new-world-of-hyatt-order-coffee-break-ep107-5-26-26/",
      "thumbnailUrl": "https://frequentmiler.com/wp-content/uploads/2026/05/First-impressions-of-the-new-World-of-Hyatt-order-2.jpg",
      "category": "Card Updates",
      "publishedAt": "2026-05-26T22:45:43Z",
      "source": "Frequent Miler"
    },
    {
      "id": "0e1be13fb68196f8",
      "title": "The United Quest\u2120 Card Review: Extensive Travel Benefits That Offset the Annual Fee",
      "summary": "The United Quest\u2120 Card is the Goldilocks option in Chase\u2019s lineup of MileagePlus credit cards.",
      "url": "https://awardwallet.com/credit-cards/united-mileageplus/united-quest-card/?pubDate=2026-05-26",
      "thumbnailUrl": null,
      "category": "Tips",
      "publishedAt": "2026-05-26T22:10:03Z",
      "source": "AwardWallet"
    },
    {
      "id": "8814d6dcc809f629",
      "title": "TheGiftCardShop.com: Get waived purchase fees on Visa & Mastercard gift cards with code GRADS26",
      "summary": "A couple of weeks ago, several Incomm-run stores\u2014MastercardGiftCard.com, VanillaGift.com, and AmexGiftCard.com\u2014launched sales waiving purch\u2026",
      "url": "https://frequentmiler.com/thegiftcardshop-com-get-waived-purchase-fees-on-visa-mastercard-gift-cards-with-code-grads26/",
      "thumbnailUrl": "https://frequentmiler.com/wp-content/uploads/2026/05/TheGiftCardShop-promo-code-GRADS26.png",
      "category": "Deals",
      "publishedAt": "2026-05-26T21:45:05Z",
      "source": "Frequent Miler"
    },
    {
      "id": "dc502c63699bc7a7",
      "title": "Best airport lounge access credit cards: 4 picks for frequent flyers",
      "summary": "Compare the best airport lounge access credit cards for frequent flyers, including Amex Platinum, Sapphire Reserve, Citi AAdvantage Executi\u2026",
      "url": "https://thepointsguy.com/credit-cards/best-rewards-credit-cards-for-lounge-access/",
      "thumbnailUrl": "https://runway-media-production.global.ssl.fastly.net/us/originals/2025/09/20250915_Tokyo-Haneda-Amex-Centurion-Lounge_CHenderson-41.jpg",
      "category": "News",
      "publishedAt": "2026-05-26T21:00:32Z",
      "source": "The Points Guy"
    },
    {
      "id": "76f0a88528ada17a",
      "title": "Is The Amex Gold Card Worth $325? 4x Points & $424 In Credits Says Yes",
      "summary": "The American Express Gold Card (application) has a $325 annual fee ( Rates & Fees ), which is obviously on the steep side.",
      "url": "https://onemileatatime.com/insights/american-express-gold-card-worth-it/",
      "thumbnailUrl": "https://cdn.onemileatatime.com/wp-content/uploads/2021/03/Thompson-Dallas-38-1.jpeg?width=1200&quality=75&height=841&aspect_ratio=1200%3A841",
      "category": "Tips",
      "publishedAt": "2026-05-26T20:47:02Z",
      "source": "One Mile at a Time"
    },
    {
      "id": "9b6dcc1269c18b5e",
      "title": "Hyatt launched targeted bonus points offers, but you might want to wait to register",
      "summary": "Check your World of Hyatt account for new targeted bonus points offers.",
      "url": "https://thepointsguy.com/news/world-of-hyatt-targeted-bonus-points-promotion/",
      "thumbnailUrl": "https://runway-media-production.global.ssl.fastly.net/us/originals/2020/08/Ventana-Big-Sur-Zach-Griff-46.jpg",
      "category": "Deals",
      "publishedAt": "2026-05-26T20:30:40Z",
      "source": "The Points Guy"
    },
    {
      "id": "cfefbcadd3108f17",
      "title": "New Partnership Unlocks 6k Awards Within Southeast Asia (Amex, Bilt, Capital One, Citi, or Rove Points)",
      "summary": "Etihad Guest has just launched a new frequent flyer partnership with Bangkok Airways\u2019 FlyerBonus.",
      "url": "https://awardwallet.com/news/airlines/etihad-bangkok-partnership/?pubDate=2026-05-26",
      "thumbnailUrl": null,
      "category": "Card Updates",
      "publishedAt": "2026-05-26T20:00:55Z",
      "source": "AwardWallet"
    },
    {
      "id": "00d0f043df437b86",
      "title": "Planning a destination wedding? Earn 120K-300K IHG One Rewards points at participating IHG properties",
      "summary": "If you\u2019re planning on having a destination wedding, IHG currently has a promotion that can earn you up to 300,000 bonus IHG One Rewards poi\u2026",
      "url": "https://frequentmiler.com/planning-a-destination-wedding-earn-120k-300k-ihg-one-rewards-points-at-participating-ihg-properties/",
      "thumbnailUrl": "https://frequentmiler.com/wp-content/uploads/2026/05/IHG-One-Rewards-wedding-honeymoon-promotion.png",
      "category": "Deals",
      "publishedAt": "2026-05-26T19:45:17Z",
      "source": "Frequent Miler"
    },
    {
      "id": "a0edbc0122d0d3ec",
      "title": "Ending Soon: Capital One Venture Business Limited-Time Offer of up to 150k Bonus Miles",
      "summary": "There\u2019s a brand-new business card on the market, and it\u2019s rewarding to spend on, earns valuable miles, and offers easy-to-use benefits that\u2026",
      "url": "https://awardwallet.com/credit-cards/capital-one-rewards/venture-business/?pubDate=2026-05-26",
      "thumbnailUrl": null,
      "category": "Deals",
      "publishedAt": "2026-05-26T19:00:54Z",
      "source": "AwardWallet"
    },
    {
      "id": "b18cab8ce6bf3bf5",
      "title": "New Capital One Venture Business With Up To 150K Miles (Last Chance To Apply)",
      "summary": "TheCapital One Venture Business launched several weeks ago, and is a rebranded version of the former Capital One Spark Miles, with some ver\u2026",
      "url": "https://onemileatatime.com/guides/venture-business/",
      "thumbnailUrl": "https://cdn.onemileatatime.com/wp-content/uploads/2022/03/American-Airlines-First-Class-Hawaii-27-3.jpeg?width=1200&quality=75&height=855&aspect_ratio=80%3A57",
      "category": "Card Updates",
      "publishedAt": "2026-05-26T18:12:00Z",
      "source": "One Mile at a Time"
    },
    {
      "id": "afc3fc92c920bf72",
      "title": "Air France-KLM Flying Blue Paid Status Match Promotion: Eligibility, Cost, Value",
      "summary": "For quite some time, Air France-KLM Flying Blue has been offering paid status match promotions, on an on-again, off-again basis.",
      "url": "https://onemileatatime.com/deals/air-france-klm-flying-blue-status-match/",
      "thumbnailUrl": "https://cdn.onemileatatime.com/wp-content/uploads/2024/04/KLM-Crown-Lounge-Amsterdam-12.jpeg?width=1200&quality=75&height=900&aspect_ratio=4%3A3",
      "category": "Deals",
      "publishedAt": "2026-05-26T18:11:42Z",
      "source": "One Mile at a Time"
    },
    {
      "id": "755dba27bc368b4c",
      "title": "Deal of the day: Fly to Alaska from 12,500 Atmos Rewards points this summer",
      "summary": "You can save on flights to Alaska with this Alaska Airlines Atmos Rewards deal.",
      "url": "https://thepointsguy.com/deals/deal-of-the-day/",
      "thumbnailUrl": "https://runway-media-production.global.ssl.fastly.net/us/originals/2026/05/GettyImages-1498252195.jpg",
      "category": "Deals",
      "publishedAt": "2026-05-26T18:05:38Z",
      "source": "The Points Guy"
    },
    {
      "id": "01739193f0a3a140",
      "title": "(Update) Capital One Rebrands Spark Miles & Spark Miles Select to Venture Business and VentureOne Business (150k Bonus)",
      "summary": "Update 5/26/26: The 150,000 signup bonus on Venture Business is slated to end 6/8/26.",
      "url": "https://www.doctorofcredit.com/capital-one-rebrands-spark-miles-spark-miles-select-to-venture-business-and-ventureone-business/",
      "thumbnailUrl": null,
      "category": "Deals",
      "publishedAt": "2026-05-26T17:26:35Z",
      "source": "Doctor of Credit"
    },
    {
      "id": "4d4b420eb9bc52ec",
      "title": "Chase Sapphire Reserve statement credits: What they are and how to use them",
      "summary": "The Chase Sapphire Reserve is one of our top picks for premium travel cards.",
      "url": "https://thepointsguy.com/credit-cards/chase-sapphire-reserve-credits/",
      "thumbnailUrl": "https://runway-media-production.global.ssl.fastly.net/us/originals/2024/08/PEOPLE-IN-LINE-AT-HOTEL-RECEPTION-TO-CHECK-IN-AND-OUT_Maskot.jpg",
      "category": "Tips",
      "publishedAt": "2026-05-26T17:00:37Z",
      "source": "The Points Guy"
    },
    {
      "id": "31ac521dde6cad9e",
      "title": "What You Get by Signing Up for the Free Bilt Rewards Program and Why You Should",
      "summary": "Bilt Rewards is a flexible point currency like American Express Membership Rewards and Chase Ultimate Rewards.",
      "url": "https://awardwallet.com/credit-cards/bilt-rewards/what-is-bilt-rewards/?pubDate=2026-05-26",
      "thumbnailUrl": null,
      "category": "Tips",
      "publishedAt": "2026-05-26T16:10:01Z",
      "source": "AwardWallet"
    },
    {
      "id": "c87ca7d44fb96820",
      "title": "Breeze Airways promo: Save 45% on round trip base fares with promo code BIRTHDAY",
      "summary": "Breeze Airways is out with another new airfare deal, this time giving a 45% discount on round-trip base fares when using promo code BIRTHDA\u2026",
      "url": "https://frequentmiler.com/breeze-airways-promo/",
      "thumbnailUrl": "https://frequentmiler.com/wp-content/uploads/2023/08/Breeze-Airways-airplane.jpg",
      "category": "Deals",
      "publishedAt": "2026-05-26T15:45:03Z",
      "source": "Frequent Miler"
    },
    {
      "id": "650c101c784b7a67",
      "title": "How My First Time Sneaking Into An Airport Lounge Opened The Door To A Lifetime Of VIP Travel",
      "summary": "While I write about lounges a lot, I didn't always have access.",
      "url": "https://viewfromthewing.com/how-my-first-time-sneaking-into-an-airport-lounge-opened-the-door-to-a-lifetime-of-vip-travel/",
      "thumbnailUrl": "https://viewfromthewing.com/wp-content/uploads/2023/09/Lounge2.jpg",
      "category": "News",
      "publishedAt": "2026-05-26T15:04:17Z",
      "source": "View from the Wing"
    },
    {
      "id": "628a805a549ebcde",
      "title": "Caesars Rewards Amex Offer: Spend $200 & get $40 back",
      "summary": "A new Caesars Rewards Amex Offer appeared yesterday for targeted cardholders which is offering $40 back when spending $200 or more.",
      "url": "https://frequentmiler.com/caesars-rewards-amex-offer-spend-200-get-40-back/",
      "thumbnailUrl": "https://frequentmiler.com/wp-content/uploads/2022/04/Untitled-design-2022-04-15T142610.696.jpg",
      "category": "Deals",
      "publishedAt": "2026-05-26T14:45:32Z",
      "source": "Frequent Miler"
    },
    {
      "id": "6284973ba40d2a73",
      "title": "Hotel Promotions Roundup: Free Nights and Bonus Points with Hilton, Marriott, Hyatt, GHA, & More",
      "summary": "Do you find it difficult to track all the hotel promotions that are currently available?",
      "url": "https://awardwallet.com/news/hotels/current-hotel-promotions/?pubDate=2026-05-26",
      "thumbnailUrl": null,
      "category": "Deals",
      "publishedAt": "2026-05-26T14:10:02Z",
      "source": "AwardWallet"
    },
    {
      "id": "d02c7d54a224bf24",
      "title": "Save $50 with JetBlue Citi Offer when spending $400+",
      "summary": "There\u2019s a new JetBlue Citi Offer that\u2019s once again giving $50 back as a statement credit.",
      "url": "https://frequentmiler.com/save-50-with-jetblue-citi-offer-when-spending-400/",
      "thumbnailUrl": "https://frequentmiler.com/wp-content/uploads/2026/05/JetBlue-Citi-Offer-spend-400-get-50.jpg",
      "category": "Deals",
      "publishedAt": "2026-05-26T13:45:50Z",
      "source": "Frequent Miler"
    },
    {
      "id": "bf143c9a6dbbdae5",
      "title": "Oh My: Marriott Bonvoy Gold Member Blasts Hotel Over Intimacy Problems",
      "summary": "OMAAT reader Paul pointed me to a hotel review that kind of cracked me up, and I imagine others will get a kick out of it as well\u2026",
      "url": "https://onemileatatime.com/news/marriott-bonvoy-gold-member-blasts-hotel-intimacy-problems/",
      "thumbnailUrl": "https://cdn.onemileatatime.com/wp-content/uploads/2026/05/Kananaskis-Hotel.jpg?width=1200&quality=75&height=799&aspect_ratio=1200%3A799",
      "category": "Tips",
      "publishedAt": "2026-05-26T13:25:09Z",
      "source": "One Mile at a Time"
    },
    {
      "id": "f8aba47ea5652377",
      "title": "Take Advantage of Capital One Venture X\u2019s Lesser-Known Benefits",
      "summary": "You may have heard about lounge access, bonus miles, and a travel credit, but did you know that the Capital One Venture X Rewards Credit Ca\u2026",
      "url": "https://awardwallet.com/credit-cards/capital-one-rewards/venture-x-benefits/?pubDate=2026-05-26",
      "thumbnailUrl": null,
      "category": "Tips",
      "publishedAt": "2026-05-26T12:10:02Z",
      "source": "AwardWallet"
    },
    {
      "id": "b29a831d83464444",
      "title": "Miraval Austin: Bottom Line Review",
      "summary": "Miraval is Hyatt\u2019s \u201cwellness\u201d brand, with three locations in the US and one in the Middle East.",
      "url": "https://frequentmiler.com/miraval-austin-bottom-line-review/",
      "thumbnailUrl": "https://frequentmiler.com/wp-content/uploads/2026/05/Miraval-Austin-Featured-Image.jpg",
      "category": "Tips",
      "publishedAt": "2026-05-26T01:45:47Z",
      "source": "Frequent Miler"
    },
    {
      "id": "ddece9fdd378010a",
      "title": "Earn 75,000 Bonus Miles With the Capital One Venture X Rewards Credit Card",
      "summary": "The Capital One Venture X Rewards Credit Card is offering new applicants 75,000 bonus miles when you spend $4,000 on purchases in the first\u2026",
      "url": "https://awardwallet.com/credit-cards/capital-one-rewards/venture-x-offer/?pubDate=2026-05-25",
      "thumbnailUrl": null,
      "category": "Deals",
      "publishedAt": "2026-05-25T23:51:51Z",
      "source": "AwardWallet"
    },
    {
      "id": "c03ec8b05767c638",
      "title": "60K Choice Privileges points with no annual fee with new Choice Mastercard offer",
      "summary": "The Choice Privileges Mastercard is currently featuring an increased introductory offer of 60,000 Choice Privileges points after spending $\u2026",
      "url": "https://frequentmiler.com/60k-choice-privileges-points-with-no-annual-fee-with-new-choice-mastercard-offer/",
      "thumbnailUrl": "https://frequentmiler.com/wp-content/uploads/2026/05/Choice-60K-offer-no-annual-fee.png",
      "category": "Card Updates",
      "publishedAt": "2026-05-25T21:45:52Z",
      "source": "Frequent Miler"
    },
    {
      "id": "7339cfc1e872a792",
      "title": "What Alaska Atmos Rewards Points Are Worth \u2014 and How To Get Top Value",
      "summary": "Of all the airline points you can earn \u2014 and there's a lot \u2014 Alaska Airlines Atmos Rewards points are some of the most valuable.",
      "url": "https://awardwallet.com/airlines/alaska-atmos-rewards/alaska-miles-value/?pubDate=2026-05-25",
      "thumbnailUrl": null,
      "category": "Tips",
      "publishedAt": "2026-05-25T21:10:02Z",
      "source": "AwardWallet"
    },
    {
      "id": "34ed74e2d38ab778",
      "title": "An Austin Permit Points Southwest Airlines Completing An Airport Lounge By March",
      "summary": "Southwest Airlines has never had airport lounges, but a new Austin permit suggests that is about to change sooner than expected.",
      "url": "https://viewfromthewing.com/an-austin-permit-points-southwest-airlines-completing-an-airport-lounge-by-march/",
      "thumbnailUrl": "https://viewfromthewing.com/wp-content/uploads/2019/10/southwest-airlines-effects.jpg",
      "category": "News",
      "publishedAt": "2026-05-25T21:04:33Z",
      "source": "View from the Wing"
    },
    {
      "id": "2bd9774ff4d62118",
      "title": "Targeted Hyatt promos: 2K every 2 nights up to 20K; 3X points on stays 2+ nights, more",
      "summary": "World of Hyatt is out with some targeted promotions to earn bonus points on stays.",
      "url": "https://frequentmiler.com/targeted-hyatt-promos-2k-every-2-nights-up-to-20k-3x-points-on-stays-2-nights-more/",
      "thumbnailUrl": "https://frequentmiler.com/wp-content/uploads/2026/05/Hyatt-promo-2K-points-for-every-2-eligible-stays-up-to-20K-points.jpg",
      "category": "Deals",
      "publishedAt": "2026-05-25T19:45:29Z",
      "source": "Frequent Miler"
    },
    {
      "id": "6357938f4f239177",
      "title": "How to use your American Express Clear+ statement credit",
      "summary": "If you play your cards right, you could get a Clear+ membership for free, bring your kids for free and bring another adult for just a few b\u2026",
      "url": "https://thepointsguy.com/credit-cards/guide-to-using-the-amex-platinum-clear-credit/",
      "thumbnailUrl": "https://runway-media-production.global.ssl.fastly.net/us/originals/2023/06/CLEAR_FACEBOOK_2.jpeg",
      "category": "Tips",
      "publishedAt": "2026-05-25T19:00:59Z",
      "source": "The Points Guy"
    },
    {
      "id": "f8e85f6f9f396a6c",
      "title": "Chase Offers/U.S. Bank: Aldi 5% Back ($3 Cashback Max)",
      "summary": "Earn 10% cash back on your Aldi purchase, with a $6.00 cash back maximum.",
      "url": "https://www.doctorofcredit.com/chase-offers-bofa-aldi-10-back-6-cashback-max/",
      "thumbnailUrl": null,
      "category": "Deals",
      "publishedAt": "2026-05-25T18:46:29Z",
      "source": "Doctor of Credit"
    },
    {
      "id": "d6588c2b19522e2f",
      "title": "Chase Sapphire Reserve\u00ae Application Rules That Can Make or Break Your Approval",
      "summary": "If you're looking for information on how to get the Chase Sapphire Reserve\u00ae, we've got you covered.",
      "url": "https://awardwallet.com/credit-cards/chase-ultimate-rewards/how-to-get-chase-sapphire-reserve/?pubDate=2026-05-25",
      "thumbnailUrl": null,
      "category": "Tips",
      "publishedAt": "2026-05-25T18:10:02Z",
      "source": "AwardWallet"
    },
    {
      "id": "98c9c03b9c9a5a31",
      "title": "Capital One Shopping: Get 45% Back On Viator (Tours, Transfers, Activities)",
      "summary": "Capital One Shopping portal is offering 45%-50% back on Viator bookings.",
      "url": "https://www.doctorofcredit.com/capital-one-shopping-get-45-50-back-on-viator-tours-transfers-activities/",
      "thumbnailUrl": null,
      "category": "Deals",
      "publishedAt": "2026-05-25T18:07:35Z",
      "source": "Doctor of Credit"
    },
    {
      "id": "5943b8d5b82c91ad",
      "title": "Rakuten+ subscription: 10% back at select merchants for $100/yr, with a $50 signup bonus",
      "summary": "Doctor of Credit has uncovered something that will only be of interest to a subset of readers: Rakuten offers a Rakuten+ subscription.",
      "url": "https://frequentmiler.com/rakuten-subscription-10-back-at-select-merchants-for-100-yr-with-a-50-signup-bonus/",
      "thumbnailUrl": "https://frequentmiler.com/wp-content/uploads/2026/05/Rakuten-Plus-join-the-waitlist-scaled.jpg",
      "category": "Deals",
      "publishedAt": "2026-05-25T17:45:48Z",
      "source": "Frequent Miler"
    }
  ]
}
